venvmgr/cli.py
venvmgr/config.py
venvmgr/venvmgr.py
venvmgr-0.1.2.dist-info/LICENSE
venvmgr-0.1.2.dist-info/METADATA
venvmgr-0.1.2.dist-info/WHEEL
venvmgr-0.1.2.dist-info/entry_points.txt
venvmgr-0.1.2.dist-info/top_level.txt
venvmgr-0.1.2.dist-info/RECORD
