Metadata-Version: 2.1
Name: venvmgr
Version: 0.1.2
Summary: Manage Python virtual environments
Home-page: https://github.com/andrewfowlie/venvmgr
Author: Andrew Fowlie
Author-email: Andrew Fowlie <andrew.fowlie@xjtlu.edu.cn>
License: MIT License
Project-URL: Bug Tracker, https://github.com/andrewfowlie/venvmgr/issues
Classifier: Programming Language :: Python :: 3
Classifier: License :: OSI Approved :: MIT License
Classifier: Operating System :: OS Independent
License-File: LICENSE
Requires-Dist: click
